LICENSE
MANIFEST.in
README.md
requirements.txt
setup.py
gnlse/__init__.py
gnlse/common.py
gnlse/dispersion.py
gnlse/envelopes.py
gnlse/gnlse.py
gnlse/import_export.py
gnlse/nonlinearity.py
gnlse/raman_response.py
gnlse/visualization.py
gnlse.egg-info/PKG-INFO
gnlse.egg-info/SOURCES.txt
gnlse.egg-info/dependency_links.txt
gnlse.egg-info/requires.txt
gnlse.egg-info/top_level.txt