Metadata-Version: 2.1
Name: gnlse
Version: 2.0.0
Summary: gnlse-python is a Python set of scripts for solving Generalized Nonlinear Schrodringer Equation
Home-page: https://github.com/WUST-FOG/gnlse-python
Author: Redman, P., Zatorska, M., Pawlowski, A., Szulc, D., Majchrowska, S., Tarnowski, K.
License: UNKNOWN
Platform: UNKNOWN
Classifier: Programming Language :: Python :: 3
Classifier: License :: OSI Approved :: MIT License
Classifier: Operating System :: OS Independent
Requires-Python: >=3.7
License-File: LICENSE
